satsync/__init__.py
satsync/ecc.py
satsync/lgm.py
satsync/lightglue/__init__.py
satsync/lightglue/aliked.py
satsync/lightglue/disk.py
satsync/lightglue/dog_hardnet.py
satsync/lightglue/lightglue.py
satsync/lightglue/sift.py
satsync/lightglue/superpoint.py
satsync/lightglue/utils.py
satsync/lightglue/viz2d.py
satsync/main.py
satsync/pcc.py
satsync/utils.py
satsync-0.0.7.dist-info/LICENSE
satsync-0.0.7.dist-info/WHEEL
satsync-0.0.7.dist-info/METADATA
satsync-0.0.7.dist-info/RECORD
