Metadata-Version: 2.1
Name: satsync
Version: 0.0.7
Summary: Methods for spatial alignment of satellite imagery
Home-page: https://github.com/csaybar/satsync
Author: Cesar Aybar
Author-email: fcesar.aybar@uv.es
Requires-Python: >=3.10,<4.0
Classifier: Programming Language :: Python :: 3
Classifier: Programming Language :: Python :: 3.10
Requires-Dist: kornia (>=0.7.2)
Requires-Dist: numpy (>=1.25.2)
Requires-Dist: opencv-python (>=4.8.0.76)
Requires-Dist: pandas (>=2.0.3)
Requires-Dist: rasterio (>=1.3.10)
Requires-Dist: scikit-image (>=0.23.1)
Requires-Dist: torch (>=2.0.0)
Requires-Dist: xarray (>=2023.7.0)
Project-URL: Documentation, https://csaybar.github.io/satsync/
Project-URL: Repository, https://github.com/csaybar/satsync
